happytransformer/__init__.py
happytransformer/args.py
happytransformer/fine_tuning_util.py
happytransformer/happy_generation.py
happytransformer/happy_next_sentence.py
happytransformer/happy_question_answering.py
happytransformer/happy_text_classification.py
happytransformer/happy_text_to_text.py
happytransformer/happy_token_classification.py
happytransformer/happy_transformer.py
happytransformer/happy_word_prediction.py
happytransformer/adaptors/__init__.py
happytransformer/adaptors/adaptor.py
happytransformer/adaptors/berts.py
happytransformer-3.0.1.dist-info/licenses/LICENSE
happytransformer-3.0.1.dist-info/METADATA
happytransformer-3.0.1.dist-info/WHEEL
happytransformer-3.0.1.dist-info/top_level.txt
happytransformer-3.0.1.dist-info/RECORD
