Metadata-Version: 2.4
Name: happytransformer
Version: 3.0.1
Summary: Happy Transformer makes it easy to fine-tune and perform inference with NLP Transformer models.
Author-email: The Happy Transformer Development Team <happytransformer@gmail.com>
License: Apache 2.0
Project-URL: Homepage, https://happytransformer.com
Project-URL: Repository, https://github.com/EricFillion/happy-transformer
Keywords: ai,transformer,happy,HappyTransformer,classification,nlp,nlu,training,fine-tuning
Classifier: Intended Audience :: Developers
Classifier: Intended Audience :: Science/Research
Classifier: License :: OSI Approved :: Apache Software License
Classifier: Programming Language :: Python :: 3
Classifier: Programming Language :: Python :: 3.10
Classifier: Programming Language :: Python :: 3.11
Classifier: Programming Language :: Python :: 3.12
Classifier: Programming Language :: Python :: 3.13
Classifier: Topic :: Text Processing :: Linguistic
Classifier: Topic :: Scientific/Engineering :: Artificial Intelligence
License-File: LICENSE
Requires-Dist: torch>=2.2
Requires-Dist: tqdm>=4.43
Requires-Dist: transformers<5.0.0,>=4.46.0
Requires-Dist: datasets<3.0.0,>=2.15.0
Requires-Dist: dataclasses; python_version < "3.7"
Requires-Dist: sentencepiece
Requires-Dist: protobuf
Requires-Dist: accelerate<2.0.0,>=1.3.0
Requires-Dist: tokenizers<1.0.0,>=0.20.0
Requires-Dist: wandb
Dynamic: license-file
